c7n_awscc/__init__.py
c7n_awscc/actions.py
c7n_awscc/entry.py
c7n_awscc/manager.py
c7n_awscc/meta.py
c7n_awscc/provider.py
c7n_awscc/query.py
c7n_awscc/data/alexa_ask_skill.json
c7n_awscc/data/aws_accessanalyzer_analyzer.json
c7n_awscc/data/aws_acmpca_certificate.json
c7n_awscc/data/aws_acmpca_certificateauthority.json
c7n_awscc/data/aws_acmpca_certificateauthorityactivation.json
c7n_awscc/data/aws_acmpca_permission.json
c7n_awscc/data/aws_aiops_investigationgroup.json
c7n_awscc/data/aws_amazonmq_broker.json
c7n_awscc/data/aws_amazonmq_configuration.json
c7n_awscc/data/aws_amazonmq_configurationassociation.json
c7n_awscc/data/aws_amplify_app.json
c7n_awscc/data/aws_amplify_branch.json
c7n_awscc/data/aws_amplify_domain.json
c7n_awscc/data/aws_amplifyuibuilder_component.json
c7n_awscc/data/aws_amplifyuibuilder_form.json
c7n_awscc/data/aws_amplifyuibuilder_theme.json
c7n_awscc/data/aws_apigateway_account.json
c7n_awscc/data/aws_apigateway_apikey.json
c7n_awscc/data/aws_apigateway_authorizer.json
c7n_awscc/data/aws_apigateway_basepathmapping.json
c7n_awscc/data/aws_apigateway_basepathmappingv2.json
c7n_awscc/data/aws_apigateway_clientcertificate.json
c7n_awscc/data/aws_apigateway_deployment.json
c7n_awscc/data/aws_apigateway_documentationpart.json
c7n_awscc/data/aws_apigateway_documentationversion.json
c7n_awscc/data/aws_apigateway_domainname.json
c7n_awscc/data/aws_apigateway_domainnameaccessassociation.json
c7n_awscc/data/aws_apigateway_domainnamev2.json
c7n_awscc/data/aws_apigateway_gatewayresponse.json
c7n_awscc/data/aws_apigateway_method.json
c7n_awscc/data/aws_apigateway_model.json
c7n_awscc/data/aws_apigateway_requestvalidator.json
c7n_awscc/data/aws_apigateway_resource.json
c7n_awscc/data/aws_apigateway_restapi.json
c7n_awscc/data/aws_apigateway_stage.json
c7n_awscc/data/aws_apigateway_usageplan.json
c7n_awscc/data/aws_apigateway_usageplankey.json
c7n_awscc/data/aws_apigateway_vpclink.json
c7n_awscc/data/aws_apigatewayv2_api.json
c7n_awscc-0.1.34.dist-info/METADATA
c7n_awscc-0.1.34.dist-info/WHEEL
c7n_awscc-0.1.34.dist-info/RECORD
